pyfaup/__init__.py
pyfaup/__init__.pyi
pyfaup/py.typed
pyfaup/pyfaup.cpython-313-s390x-linux-gnu.so
pyfaup_rs-0.2.0.dist-info/METADATA
pyfaup_rs-0.2.0.dist-info/WHEEL
pyfaup_rs-0.2.0.dist-info/RECORD
