Metadata-Version: 2.4
Name: pyfaup-rs
Version: 0.2.0
Classifier: Programming Language :: Rust
Classifier: Programming Language :: Python :: Implementation :: CPython
Classifier: Programming Language :: Python :: Implementation :: PyPy
Summary: Python bindings for faup-rs Rust library
Author-email: Quentin JEROME <quentin.jerome@circl.lu>
Maintainer-email: Quentin JEROME <quentin.jerome@circl.lu>
License-Expression: GPL-3.0
Requires-Python: >=3.8
Project-URL: Repository, https://github.com/ail-project/faup-rs
